[{"normalization": 1, "date": "scissors", "extrator": "PHOG", "classifier": "Gaussian Naive Bayes", "treinamento": "0.33", "teste": "0.33", "precision": "0.10959", "recall": "0.33333", "f1_score": "0.16495", "runningtime": "0.00496"}, {"normalization": 1, "date": "scissors", "extrator": "PHOG", "classifier": "Logistic Regression", "treinamento": "0.34", "teste": "0.34", "precision": "0.36163", "recall": "0.34783", "f1_score": "0.19464", "runningtime": "0.11036"}, {"normalization": 1, "date": "scissors", "extrator": "PHOG", "classifier": "Decision Tree", "treinamento": "0.22", "teste": "0.22", "precision": "0.13571", "recall": "0.22454", "f1_score": "0.16575", "runningtime": "0.01450"}, {"normalization": 1, "date": "scissors", "extrator": "PHOG", "classifier": "K-Nearest Neighbors", "treinamento": "0.33", "teste": "0.33", "precision": "0.10959", "recall": "0.33333", "f1_score": "0.16495", "runningtime": "0.09795"}, {"normalization": 1, "date": "scissors", "extrator": "PHOG", "classifier": "Linear Discriminant Analysis", "treinamento": "0.49", "teste": "0.44", "precision": "0.31844", "recall": "0.44867", "f1_score": "0.35115", "runningtime": "0.01507"}, {"normalization": 1, "date": "scissors", "extrator": "PHOG", "classifier": "Support Vector Machine", "treinamento": "0.33", "teste": "0.33", "precision": "0.10959", "recall": "0.33333", "f1_score": "0.16495", "runningtime": "0.00903"}, {"normalization": 1, "date": "scissors", "extrator": "PHOG", "classifier": "RandomForest", "treinamento": "0.54", "teste": "0.55", "precision": "0.37329", "recall": "0.56673", "f1_score": "0.44816", "runningtime": "0.01050"}, {"normalization": 1, "date": "scissors", "extrator": "PHOG", "classifier": "Neural Net", "treinamento": "0.33", "teste": "0.33", "precision": "0.10959", "recall": "0.33333", "f1_score": "0.16495", "runningtime": "0.01645"}, {"normalization": 1, "date": "scissors", "extrator": "PHOG", "classifier": "Gaussian Naive Bayes", "treinamento": "0.57", "teste": "0.55", "precision": "0.36943", "recall": "0.57015", "f1_score": "0.44500", "runningtime": "0.00509"}, {"normalization": 1, "date": "scissors", "extrator": "PHOG", "classifier": "Logistic Regression", "treinamento": "0.44", "teste": "0.44", "precision": "0.35337", "recall": "0.44928", "f1_score": "0.34062", "runningtime": "0.00376"}, {"normalization": 1, "date": "scissors", "extrator": "PHOG", "classifier": "Decision Tree", "treinamento": "0.48", "teste": "0.43", "precision": "0.40286", "recall": "0.43891", "f1_score": "0.41035", "runningtime": "0.00367"}, {"normalization": 1, "date": "scissors", "extrator": "PHOG", "classifier": "K-Nearest Neighbors", "treinamento": "0.61", "teste": "0.60", "precision": "0.42315", "recall": "0.61946", "f1_score": "0.49497", "runningtime": "0.08767"}, {"normalization": 1, "date": "scissors", "extrator": "PHOG", "classifier": "Linear Discriminant Analysis", "treinamento": "0.52", "teste": "0.52", "precision": "0.35451", "recall": "0.53684", "f1_score": "0.42540", "runningtime": "0.00518"}, {"normalization": 1, "date": "scissors", "extrator": "PHOG", "classifier": "Support Vector Machine", "treinamento": "0.33", "teste": "0.33", "precision": "0.10959", "recall": "0.33333", "f1_score": "0.16495", "runningtime": "0.00790"}, {"normalization": 1, "date": "scissors", "extrator": "PHOG", "classifier": "RandomForest", "treinamento": "0.70", "teste": "0.68", "precision": "0.73003", "recall": "0.69479", "f1_score": "0.64806", "runningtime": "0.01259"}, {"normalization": 1, "date": "scissors", "extrator": "PHOG", "classifier": "Neural Net", "treinamento": "0.54", "teste": "0.55", "precision": "0.37086", "recall": "0.56522", "f1_score": "0.44174", "runningtime": "0.01847"}, {"normalization": 1, "date": "scissors", "extrator": "PHOG", "classifier": "Gaussian Naive Bayes", "treinamento": "0.59", "teste": "0.57", "precision": "0.39036", "recall": "0.59008", "f1_score": "0.46771", "runningtime": "0.00618"}, {"normalization": 1, "date": "scissors", "extrator": "PHOG", "classifier": "Logistic Regression", "treinamento": "0.48", "teste": "0.48", "precision": "0.69444", "recall": "0.49006", "f1_score": "0.38415", "runningtime": "0.00369"}, {"normalization": 1, "date": "scissors", "extrator": "PHOG", "classifier": "Decision Tree", "treinamento": "0.55", "teste": "0.55", "precision": "0.54096", "recall": "0.55820", "f1_score": "0.54463", "runningtime": "0.00450"}, {"normalization": 1, "date": "scissors", "extrator": "PHOG", "classifier": "K-Nearest Neighbors", "treinamento": "0.72", "teste": "0.69", "precision": "0.68615", "recall": "0.69483", "f1_score": "0.68846", "runningtime": "0.07190"}, {"normalization": 1, "date": "scissors", "extrator": "PHOG", "classifier": "Linear Discriminant Analysis", "treinamento": "0.59", "teste": "0.59", "precision": "0.57963", "recall": "0.59637", "f1_score": "0.57608", "runningtime": "0.00374"}, {"normalization": 1, "date": "scissors", "extrator": "PHOG", "classifier": "Support Vector Machine", "treinamento": "0.33", "teste": "0.33", "precision": "0.10959", "recall": "0.33333", "f1_score": "0.16495", "runningtime": "0.00606"}, {"normalization": 1, "date": "scissors", "extrator": "PHOG", "classifier": "RandomForest", "treinamento": "0.56", "teste": "0.55", "precision": "0.55781", "recall": "0.56112", "f1_score": "0.47010", "runningtime": "0.00976"}, {"normalization": 1, "date": "scissors", "extrator": "PHOG", "classifier": "Neural Net", "treinamento": "0.59", "teste": "0.58", "precision": "0.38850", "recall": "0.60397", "f1_score": "0.47282", "runningtime": "0.02254"}, {"normalization": 1, "date": "scissors", "extrator": "PHOG", "classifier": "Gaussian Naive Bayes", "treinamento": "0.61", "teste": "0.58", "precision": "0.44337", "recall": "0.60135", "f1_score": "0.48961", "runningtime": "0.00509"}, {"normalization": 1, "date": "scissors", "extrator": "PHOG", "classifier": "Logistic Regression", "treinamento": "0.57", "teste": "0.57", "precision": "0.38441", "recall": "0.58937", "f1_score": "0.46164", "runningtime": "0.00447"}, {"normalization": 1, "date": "scissors", "extrator": "PHOG", "classifier": "Decision Tree", "treinamento": "0.57", "teste": "0.58", "precision": "0.57589", "recall": "0.58710", "f1_score": "0.57497", "runningtime": "0.00405"}, {"normalization": 1, "date": "scissors", "extrator": "PHOG", "classifier": "K-Nearest Neighbors", "treinamento": "0.75", "teste": "0.71", "precision": "0.70704", "recall": "0.71680", "f1_score": "0.70677", "runningtime": "0.06956"}, {"normalization": 1, "date": "scissors", "extrator": "PHOG", "classifier": "Linear Discriminant Analysis", "treinamento": "0.62", "teste": "0.62", "precision": "0.62299", "recall": "0.62054", "f1_score": "0.61330", "runningtime": "0.00381"}, {"normalization": 1, "date": "scissors", "extrator": "PHOG", "classifier": "Support Vector Machine", "treinamento": "0.33", "teste": "0.33", "precision": "0.10959", "recall": "0.33333", "f1_score": "0.16495", "runningtime": "0.00760"}, {"normalization": 1, "date": "scissors", "extrator": "PHOG", "classifier": "RandomForest", "treinamento": "0.69", "teste": "0.65", "precision": "0.64655", "recall": "0.65862", "f1_score": "0.62550", "runningtime": "0.00902"}, {"normalization": 1, "date": "scissors", "extrator": "PHOG", "classifier": "Neural Net", "treinamento": "0.62", "teste": "0.60", "precision": "0.62822", "recall": "0.62283", "f1_score": "0.49762", "runningtime": "0.00826"}, {"normalization": 1, "date": "scissors", "extrator": "PHOG", "classifier": "Gaussian Naive Bayes", "treinamento": "0.73", "teste": "0.72", "precision": "0.72995", "recall": "0.72226", "f1_score": "0.72372", "runningtime": "0.00586"}, {"normalization": 1, "date": "scissors", "extrator": "PHOG", "classifier": "Logistic Regression", "treinamento": "0.68", "teste": "0.68", "precision": "0.69983", "recall": "0.68478", "f1_score": "0.66204", "runningtime": "0.00453"}, {"normalization": 1, "date": "scissors", "extrator": "PHOG", "classifier": "Decision Tree", "treinamento": "0.53", "teste": "0.50", "precision": "0.49310", "recall": "0.49716", "f1_score": "0.48232", "runningtime": "0.00352"}, {"normalization": 1, "date": "scissors", "extrator": "PHOG", "classifier": "K-Nearest Neighbors", "treinamento": "0.75", "teste": "0.72", "precision": "0.71566", "recall": "0.72434", "f1_score": "0.71733", "runningtime": "0.07295"}, {"normalization": 1, "date": "scissors", "extrator": "PHOG", "classifier": "Linear Discriminant Analysis", "treinamento": "0.75", "teste": "0.74", "precision": "0.73064", "recall": "0.73421", "f1_score": "0.73219", "runningtime": "0.00512"}, {"normalization": 1, "date": "scissors", "extrator": "PHOG", "classifier": "Support Vector Machine", "treinamento": "0.33", "teste": "0.33", "precision": "0.10959", "recall": "0.33333", "f1_score": "0.16495", "runningtime": "0.01130"}, {"normalization": 1, "date": "scissors", "extrator": "PHOG", "classifier": "RandomForest", "treinamento": "0.73", "teste": "0.73", "precision": "0.72645", "recall": "0.73575", "f1_score": "0.72370", "runningtime": "0.00982"}, {"normalization": 1, "date": "scissors", "extrator": "PHOG", "classifier": "Neural Net", "treinamento": "0.75", "teste": "0.73", "precision": "0.72496", "recall": "0.73441", "f1_score": "0.72199", "runningtime": "0.00651"}, {"normalization": 1, "date": "shapes", "extrator": "PHOG", "classifier": "Gaussian Naive Bayes", "treinamento": "0.35", "teste": "0.43", "precision": "0.39710", "recall": "0.38333", "f1_score": "0.34921", "runningtime": "0.00322"}, {"normalization": 1, "date": "shapes", "extrator": "PHOG", "classifier": "Logistic Regression", "treinamento": "0.24", "teste": "0.28", "precision": "0.34603", "recall": "0.28611", "f1_score": "0.28394", "runningtime": "0.00224"}, {"normalization": 1, "date": "shapes", "extrator": "PHOG", "classifier": "Decision Tree", "treinamento": "0.57", "teste": "0.62", "precision": "0.61768", "recall": "0.62361", "f1_score": "0.61713", "runningtime": "0.00218"}, {"normalization": 1, "date": "shapes", "extrator": "PHOG", "classifier": "K-Nearest Neighbors", "treinamento": "0.14", "teste": "0.22", "precision": "0.27778", "recall": "0.19861", "f1_score": "0.22744", "runningtime": "0.01238"}, {"normalization": 1, "date": "shapes", "extrator": "PHOG", "classifier": "Linear Discriminant Analysis", "treinamento": "0.37", "teste": "0.40", "precision": "0.38519", "recall": "0.39306", "f1_score": "0.38108", "runningtime": "0.00250"}, {"normalization": 1, "date": "shapes", "extrator": "PHOG", "classifier": "Support Vector Machine", "treinamento": "0.35", "teste": "0.27", "precision": "0.08889", "recall": "0.33333", "f1_score": "0.14035", "runningtime": "0.00551"}, {"normalization": 1, "date": "shapes", "extrator": "PHOG", "classifier": "RandomForest", "treinamento": "0.52", "teste": "0.58", "precision": "0.58771", "recall": "0.58472", "f1_score": "0.57937", "runningtime": "0.00506"}, {"normalization": 1, "date": "shapes", "extrator": "PHOG", "classifier": "Neural Net", "treinamento": "0.32", "teste": "0.42", "precision": "0.44961", "recall": "0.41389", "f1_score": "0.42063", "runningtime": "0.00358"}, {"normalization": 1, "date": "shapes", "extrator": "PHOG", "classifier": "Gaussian Naive Bayes", "treinamento": "0.39", "teste": "0.42", "precision": "0.50462", "recall": "0.40417", "f1_score": "0.37897", "runningtime": "0.00308"}, {"normalization": 1, "date": "shapes", "extrator": "PHOG", "classifier": "Logistic Regression", "treinamento": "0.45", "teste": "0.45", "precision": "0.53434", "recall": "0.46389", "f1_score": "0.45457", "runningtime": "0.00220"}, {"normalization": 1, "date": "shapes", "extrator": "PHOG", "classifier": "Decision Tree", "treinamento": "0.60", "teste": "0.65", "precision": "0.65072", "recall": "0.66944", "f1_score": "0.65070", "runningtime": "0.00226"}, {"normalization": 1, "date": "shapes", "extrator": "PHOG", "classifier": "K-Nearest Neighbors", "treinamento": "0.61", "teste": "0.70", "precision": "0.76094", "recall": "0.73194", "f1_score": "0.69605", "runningtime": "0.01244"}, {"normalization": 1, "date": "shapes", "extrator": "PHOG", "classifier": "Linear Discriminant Analysis", "treinamento": "0.46", "teste": "0.47", "precision": "0.48039", "recall": "0.50139", "f1_score": "0.42844", "runningtime": "0.00339"}, {"normalization": 1, "date": "shapes", "extrator": "PHOG", "classifier": "Support Vector Machine", "treinamento": "0.35", "teste": "0.27", "precision": "0.08889", "recall": "0.33333", "f1_score": "0.14035", "runningtime": "0.00552"}, {"normalization": 1, "date": "shapes", "extrator": "PHOG", "classifier": "RandomForest", "treinamento": "0.56", "teste": "0.62", "precision": "0.63657", "recall": "0.63472", "f1_score": "0.61640", "runningtime": "0.00642"}, {"normalization": 1, "date": "shapes", "extrator": "PHOG", "classifier": "Neural Net", "treinamento": "0.52", "teste": "0.48", "precision": "0.54562", "recall": "0.49722", "f1_score": "0.48871", "runningtime": "0.01541"}, {"normalization": 1, "date": "shapes", "extrator": "PHOG", "classifier": "Gaussian Naive Bayes", "treinamento": "0.54", "teste": "0.52", "precision": "0.55926", "recall": "0.53611", "f1_score": "0.51518", "runningtime": "0.00308"}, {"normalization": 1, "date": "shapes", "extrator": "PHOG", "classifier": "Logistic Regression", "treinamento": "0.57", "teste": "0.50", "precision": "0.58464", "recall": "0.51389", "f1_score": "0.50529", "runningtime": "0.00218"}, {"normalization": 1, "date": "shapes", "extrator": "PHOG", "classifier": "Decision Tree", "treinamento": "0.59", "teste": "0.65", "precision": "0.65253", "recall": "0.66528", "f1_score": "0.65072", "runningtime": "0.00237"}, {"normalization": 1, "date": "shapes", "extrator": "PHOG", "classifier": "K-Nearest Neighbors", "treinamento": "0.64", "teste": "0.70", "precision": "0.76094", "recall": "0.73194", "f1_score": "0.69605", "runningtime": "0.01259"}, {"normalization": 1, "date": "shapes", "extrator": "PHOG", "classifier": "Linear Discriminant Analysis", "treinamento": "0.48", "teste": "0.55", "precision": "0.54524", "recall": "0.57917", "f1_score": "0.53409", "runningtime": "0.00267"}, {"normalization": 1, "date": "shapes", "extrator": "PHOG", "classifier": "Support Vector Machine", "treinamento": "0.35", "teste": "0.27", "precision": "0.08889", "recall": "0.33333", "f1_score": "0.14035", "runningtime": "0.00482"}, {"normalization": 1, "date": "shapes", "extrator": "PHOG", "classifier": "RandomForest", "treinamento": "0.54", "teste": "0.52", "precision": "0.60818", "recall": "0.54444", "f1_score": "0.50763", "runningtime": "0.00498"}, {"normalization": 1, "date": "shapes", "extrator": "PHOG", "classifier": "Neural Net", "treinamento": "0.60", "teste": "0.55", "precision": "0.58671", "recall": "0.56389", "f1_score": "0.54913", "runningtime": "0.00380"}, {"normalization": 1, "date": "shapes", "extrator": "PHOG", "classifier": "Gaussian Naive Bayes", "treinamento": "0.61", "teste": "0.53", "precision": "0.54198", "recall": "0.55694", "f1_score": "0.52853", "runningtime": "0.00302"}, {"normalization": 1, "date": "shapes", "extrator": "PHOG", "classifier": "Logistic Regression", "treinamento": "0.64", "teste": "0.57", "precision": "0.65801", "recall": "0.58889", "f1_score": "0.56837", "runningtime": "0.00225"}, {"normalization": 1, "date": "shapes", "extrator": "PHOG", "classifier": "Decision Tree", "treinamento": "0.59", "teste": "0.62", "precision": "0.63689", "recall": "0.63333", "f1_score": "0.61720", "runningtime": "0.00217"}, {"normalization": 1, "date": "shapes", "extrator": "PHOG", "classifier": "K-Nearest Neighbors", "treinamento": "0.66", "teste": "0.70", "precision": "0.74029", "recall": "0.73194", "f1_score": "0.69577", "runningtime": "0.01217"}, {"normalization": 1, "date": "shapes", "extrator": "PHOG", "classifier": "Linear Discriminant Analysis", "treinamento": "0.43", "teste": "0.45", "precision": "0.44709", "recall": "0.45694", "f1_score": "0.44793", "runningtime": "0.00308"}, {"normalization": 1, "date": "shapes", "extrator": "PHOG", "classifier": "Support Vector Machine", "treinamento": "0.35", "teste": "0.27", "precision": "0.08889", "recall": "0.33333", "f1_score": "0.14035", "runningtime": "0.00513"}, {"normalization": 1, "date": "shapes", "extrator": "PHOG", "classifier": "RandomForest", "treinamento": "0.62", "teste": "0.63", "precision": "0.64476", "recall": "0.65417", "f1_score": "0.63578", "runningtime": "0.00513"}, {"normalization": 1, "date": "shapes", "extrator": "PHOG", "classifier": "Neural Net", "treinamento": "0.64", "teste": "0.53", "precision": "0.58818", "recall": "0.55139", "f1_score": "0.53459", "runningtime": "0.00535"}, {"normalization": 1, "date": "shapes", "extrator": "PHOG", "classifier": "Gaussian Naive Bayes", "treinamento": "0.66", "teste": "0.63", "precision": "0.63317", "recall": "0.64861", "f1_score": "0.63855", "runningtime": "0.00400"}, {"normalization": 1, "date": "shapes", "extrator": "PHOG", "classifier": "Logistic Regression", "treinamento": "0.69", "teste": "0.62", "precision": "0.68415", "recall": "0.63333", "f1_score": "0.61905", "runningtime": "0.00325"}, {"normalization": 1, "date": "shapes", "extrator": "PHOG", "classifier": "Decision Tree", "treinamento": "0.64", "teste": "0.60", "precision": "0.63902", "recall": "0.61944", "f1_score": "0.59967", "runningtime": "0.00328"}, {"normalization": 1, "date": "shapes", "extrator": "PHOG", "classifier": "K-Nearest Neighbors", "treinamento": "0.69", "teste": "0.70", "precision": "0.74029", "recall": "0.73194", "f1_score": "0.69577", "runningtime": "0.01413"}, {"normalization": 1, "date": "shapes", "extrator": "PHOG", "classifier": "Linear Discriminant Analysis", "treinamento": "0.45", "teste": "0.52", "precision": "0.48321", "recall": "0.48611", "f1_score": "0.46809", "runningtime": "0.00249"}, {"normalization": 1, "date": "shapes", "extrator": "PHOG", "classifier": "Support Vector Machine", "treinamento": "0.35", "teste": "0.27", "precision": "0.08889", "recall": "0.33333", "f1_score": "0.14035", "runningtime": "0.00536"}, {"normalization": 1, "date": "shapes", "extrator": "PHOG", "classifier": "RandomForest", "treinamento": "0.71", "teste": "0.67", "precision": "0.67711", "recall": "0.68611", "f1_score": "0.66838", "runningtime": "0.00507"}, {"normalization": 1, "date": "shapes", "extrator": "PHOG", "classifier": "Neural Net", "treinamento": "0.69", "teste": "0.60", "precision": "0.65133", "recall": "0.61250", "f1_score": "0.60143", "runningtime": "0.00374"}, {"normalization": 2, "date": "scissors", "extrator": "PHOG", "classifier": "Gaussian Naive Bayes", "treinamento": "0.35", "teste": "0.34", "precision": "0.27829", "recall": "0.34300", "f1_score": "0.18551", "runningtime": "0.00564"}, {"normalization": 2, "date": "scissors", "extrator": "PHOG", "classifier": "Logistic Regression", "treinamento": "0.68", "teste": "0.66", "precision": "0.65550", "recall": "0.65948", "f1_score": "0.65456", "runningtime": "0.00378"}, {"normalization": 2, "date": "scissors", "extrator": "PHOG", "classifier": "Decision Tree", "treinamento": "0.34", "teste": "0.32", "precision": "0.34426", "recall": "0.31935", "f1_score": "0.23583", "runningtime": "0.00366"}, {"normalization": 2, "date": "scissors", "extrator": "PHOG", "classifier": "K-Nearest Neighbors", "treinamento": "0.51", "teste": "0.49", "precision": "0.53843", "recall": "0.49830", "f1_score": "0.47596", "runningtime": "0.07764"}, {"normalization": 2, "date": "scissors", "extrator": "PHOG", "classifier": "Linear Discriminant Analysis", "treinamento": "0.48", "teste": "0.50", "precision": "0.51303", "recall": "0.48441", "f1_score": "0.44926", "runningtime": "0.00396"}, {"normalization": 2, "date": "scissors", "extrator": "PHOG", "classifier": "Support Vector Machine", "treinamento": "0.33", "teste": "0.33", "precision": "0.44317", "recall": "0.33575", "f1_score": "0.17003", "runningtime": "0.01659"}, {"normalization": 2, "date": "scissors", "extrator": "PHOG", "classifier": "RandomForest", "treinamento": "0.59", "teste": "0.55", "precision": "0.62128", "recall": "0.56379", "f1_score": "0.51403", "runningtime": "0.01019"}, {"normalization": 2, "date": "scissors", "extrator": "PHOG", "classifier": "Neural Net", "treinamento": "0.68", "teste": "0.66", "precision": "0.67195", "recall": "0.66724", "f1_score": "0.65150", "runningtime": "0.01633"}, {"normalization": 2, "date": "scissors", "extrator": "PHOG", "classifier": "Gaussian Naive Bayes", "treinamento": "0.43", "teste": "0.43", "precision": "0.64297", "recall": "0.43251", "f1_score": "0.35890", "runningtime": "0.00517"}, {"normalization": 2, "date": "scissors", "extrator": "PHOG", "classifier": "Logistic Regression", "treinamento": "0.69", "teste": "0.67", "precision": "0.67410", "recall": "0.67780", "f1_score": "0.67191", "runningtime": "0.00377"}, {"normalization": 2, "date": "scissors", "extrator": "PHOG", "classifier": "Decision Tree", "treinamento": "0.54", "teste": "0.55", "precision": "0.56669", "recall": "0.55663", "f1_score": "0.55571", "runningtime": "0.00386"}, {"normalization": 2, "date": "scissors", "extrator": "PHOG", "classifier": "K-Nearest Neighbors", "treinamento": "0.67", "teste": "0.66", "precision": "0.70419", "recall": "0.67133", "f1_score": "0.63644", "runningtime": "0.08092"}, {"normalization": 2, "date": "scissors", "extrator": "PHOG", "classifier": "Linear Discriminant Analysis", "treinamento": "0.34", "teste": "0.35", "precision": "0.37372", "recall": "0.35237", "f1_score": "0.35384", "runningtime": "0.00510"}, {"normalization": 2, "date": "scissors", "extrator": "PHOG", "classifier": "Support Vector Machine", "treinamento": "0.45", "teste": "0.44", "precision": "0.38810", "recall": "0.44686", "f1_score": "0.34216", "runningtime": "0.01883"}, {"normalization": 2, "date": "scissors", "extrator": "PHOG", "classifier": "RandomForest", "treinamento": "0.67", "teste": "0.62", "precision": "0.63342", "recall": "0.62795", "f1_score": "0.62503", "runningtime": "0.00861"}, {"normalization": 2, "date": "scissors", "extrator": "PHOG", "classifier": "Neural Net", "treinamento": "0.72", "teste": "0.69", "precision": "0.68952", "recall": "0.69538", "f1_score": "0.68994", "runningtime": "0.01082"}, {"normalization": 2, "date": "scissors", "extrator": "PHOG", "classifier": "Gaussian Naive Bayes", "treinamento": "0.35", "teste": "0.35", "precision": "0.77855", "recall": "0.35396", "f1_score": "0.20752", "runningtime": "0.00503"}, {"normalization": 2, "date": "scissors", "extrator": "PHOG", "classifier": "Logistic Regression", "treinamento": "0.72", "teste": "0.70", "precision": "0.70119", "recall": "0.70049", "f1_score": "0.69355", "runningtime": "0.00370"}, {"normalization": 2, "date": "scissors", "extrator": "PHOG", "classifier": "Decision Tree", "treinamento": "0.64", "teste": "0.64", "precision": "0.63634", "recall": "0.64048", "f1_score": "0.63385", "runningtime": "0.00410"}, {"normalization": 2, "date": "scissors", "extrator": "PHOG", "classifier": "K-Nearest Neighbors", "treinamento": "0.68", "teste": "0.64", "precision": "0.63264", "recall": "0.64550", "f1_score": "0.63556", "runningtime": "0.08050"}, {"normalization": 2, "date": "scissors", "extrator": "PHOG", "classifier": "Linear Discriminant Analysis", "treinamento": "0.33", "teste": "0.33", "precision": "0.34920", "recall": "0.32488", "f1_score": "0.33064", "runningtime": "0.00421"}, {"normalization": 2, "date": "scissors", "extrator": "PHOG", "classifier": "Support Vector Machine", "treinamento": "0.59", "teste": "0.59", "precision": "0.70447", "recall": "0.60396", "f1_score": "0.52527", "runningtime": "0.01776"}, {"normalization": 2, "date": "scissors", "extrator": "PHOG", "classifier": "RandomForest", "treinamento": "0.64", "teste": "0.63", "precision": "0.65603", "recall": "0.63586", "f1_score": "0.61880", "runningtime": "0.00934"}, {"normalization": 2, "date": "scissors", "extrator": "PHOG", "classifier": "Neural Net", "treinamento": "0.71", "teste": "0.68", "precision": "0.68505", "recall": "0.68872", "f1_score": "0.68330", "runningtime": "0.01322"}, {"normalization": 2, "date": "scissors", "extrator": "PHOG", "classifier": "Gaussian Naive Bayes", "treinamento": "0.42", "teste": "0.40", "precision": "0.71710", "recall": "0.40385", "f1_score": "0.29627", "runningtime": "0.02392"}, {"normalization": 2, "date": "scissors", "extrator": "PHOG", "classifier": "Logistic Regression", "treinamento": "0.76", "teste": "0.73", "precision": "0.73445", "recall": "0.73030", "f1_score": "0.72381", "runningtime": "0.00991"}, {"normalization": 2, "date": "scissors", "extrator": "PHOG", "classifier": "Decision Tree", "treinamento": "0.62", "teste": "0.62", "precision": "0.62372", "recall": "0.62327", "f1_score": "0.60502", "runningtime": "0.01102"}, {"normalization": 2, "date": "scissors", "extrator": "PHOG", "classifier": "K-Nearest Neighbors", "treinamento": "0.69", "teste": "0.64", "precision": "0.63103", "recall": "0.64392", "f1_score": "0.63392", "runningtime": "0.11253"}, {"normalization": 2, "date": "scissors", "extrator": "PHOG", "classifier": "Linear Discriminant Analysis", "treinamento": "0.40", "teste": "0.38", "precision": "0.39035", "recall": "0.37798", "f1_score": "0.37847", "runningtime": "0.00399"}, {"normalization": 2, "date": "scissors", "extrator": "PHOG", "classifier": "Support Vector Machine", "treinamento": "0.69", "teste": "0.63", "precision": "0.64988", "recall": "0.64596", "f1_score": "0.59971", "runningtime": "0.01833"}, {"normalization": 2, "date": "scissors", "extrator": "PHOG", "classifier": "RandomForest", "treinamento": "0.71", "teste": "0.70", "precision": "0.73610", "recall": "0.71054", "f1_score": "0.68163", "runningtime": "0.01055"}, {"normalization": 2, "date": "scissors", "extrator": "PHOG", "classifier": "Neural Net", "treinamento": "0.73", "teste": "0.70", "precision": "0.70484", "recall": "0.70687", "f1_score": "0.69589", "runningtime": "0.00938"}, {"normalization": 2, "date": "scissors", "extrator": "PHOG", "classifier": "Gaussian Naive Bayes", "treinamento": "0.43", "teste": "0.42", "precision": "0.71953", "recall": "0.42094", "f1_score": "0.32873", "runningtime": "0.02462"}, {"normalization": 2, "date": "scissors", "extrator": "PHOG", "classifier": "Logistic Regression", "treinamento": "0.76", "teste": "0.73", "precision": "0.73440", "recall": "0.73065", "f1_score": "0.72313", "runningtime": "0.00644"}, {"normalization": 2, "date": "scissors", "extrator": "PHOG", "classifier": "Decision Tree", "treinamento": "0.60", "teste": "0.58", "precision": "0.63257", "recall": "0.58325", "f1_score": "0.55424", "runningtime": "0.00541"}, {"normalization": 2, "date": "scissors", "extrator": "PHOG", "classifier": "K-Nearest Neighbors", "treinamento": "0.70", "teste": "0.66", "precision": "0.64917", "recall": "0.66192", "f1_score": "0.64933", "runningtime": "0.10234"}, {"normalization": 2, "date": "scissors", "extrator": "PHOG", "classifier": "Linear Discriminant Analysis", "treinamento": "0.42", "teste": "0.40", "precision": "0.39783", "recall": "0.39945", "f1_score": "0.39663", "runningtime": "0.00401"}, {"normalization": 2, "date": "scissors", "extrator": "PHOG", "classifier": "Support Vector Machine", "treinamento": "0.71", "teste": "0.68", "precision": "0.68313", "recall": "0.69111", "f1_score": "0.66302", "runningtime": "0.01909"}, {"normalization": 2, "date": "scissors", "extrator": "PHOG", "classifier": "RandomForest", "treinamento": "0.68", "teste": "0.65", "precision": "0.67736", "recall": "0.66245", "f1_score": "0.63551", "runningtime": "0.01010"}, {"normalization": 2, "date": "scissors", "extrator": "PHOG", "classifier": "Neural Net", "treinamento": "0.73", "teste": "0.70", "precision": "0.70106", "recall": "0.70214", "f1_score": "0.69167", "runningtime": "0.01498"}, {"normalization": 2, "date": "shapes", "extrator": "PHOG", "classifier": "Gaussian Naive Bayes", "treinamento": "0.35", "teste": "0.27", "precision": "0.08889", "recall": "0.33333", "f1_score": "0.14035", "runningtime": "0.01728"}, {"normalization": 2, "date": "shapes", "extrator": "PHOG", "classifier": "Logistic Regression", "treinamento": "0.64", "teste": "0.55", "precision": "0.55556", "recall": "0.56111", "f1_score": "0.55250", "runningtime": "0.01252"}, {"normalization": 2, "date": "shapes", "extrator": "PHOG", "classifier": "Decision Tree", "treinamento": "0.50", "teste": "0.40", "precision": "0.43714", "recall": "0.42361", "f1_score": "0.39095", "runningtime": "0.00328"}, {"normalization": 2, "date": "shapes", "extrator": "PHOG", "classifier": "K-Nearest Neighbors", "treinamento": "0.51", "teste": "0.55", "precision": "0.56896", "recall": "0.54583", "f1_score": "0.54136", "runningtime": "0.02627"}, {"normalization": 2, "date": "shapes", "extrator": "PHOG", "classifier": "Linear Discriminant Analysis", "treinamento": "0.28", "teste": "0.27", "precision": "0.26717", "recall": "0.25972", "f1_score": "0.26227", "runningtime": "0.00350"}, {"normalization": 2, "date": "shapes", "extrator": "PHOG", "classifier": "Support Vector Machine", "treinamento": "0.54", "teste": "0.50", "precision": "0.63626", "recall": "0.52917", "f1_score": "0.50363", "runningtime": "0.00546"}, {"normalization": 2, "date": "shapes", "extrator": "PHOG", "classifier": "RandomForest", "treinamento": "0.49", "teste": "0.55", "precision": "0.56797", "recall": "0.55278", "f1_score": "0.54409", "runningtime": "0.00777"}, {"normalization": 2, "date": "shapes", "extrator": "PHOG", "classifier": "Neural Net", "treinamento": "0.68", "teste": "0.60", "precision": "0.62159", "recall": "0.60833", "f1_score": "0.59850", "runningtime": "0.01036"}, {"normalization": 2, "date": "shapes", "extrator": "PHOG", "classifier": "Gaussian Naive Bayes", "treinamento": "0.37", "teste": "0.32", "precision": "0.76023", "recall": "0.38056", "f1_score": "0.23339", "runningtime": "0.00450"}, {"normalization": 2, "date": "shapes", "extrator": "PHOG", "classifier": "Logistic Regression", "treinamento": "0.68", "teste": "0.55", "precision": "0.56820", "recall": "0.56111", "f1_score": "0.55332", "runningtime": "0.00301"}, {"normalization": 2, "date": "shapes", "extrator": "PHOG", "classifier": "Decision Tree", "treinamento": "0.48", "teste": "0.50", "precision": "0.51889", "recall": "0.51806", "f1_score": "0.49980", "runningtime": "0.00311"}, {"normalization": 2, "date": "shapes", "extrator": "PHOG", "classifier": "K-Nearest Neighbors", "treinamento": "0.57", "teste": "0.68", "precision": "0.73739", "recall": "0.70833", "f1_score": "0.68242", "runningtime": "0.02886"}, {"normalization": 2, "date": "shapes", "extrator": "PHOG", "classifier": "Linear Discriminant Analysis", "treinamento": "0.33", "teste": "0.25", "precision": "0.24883", "recall": "0.25139", "f1_score": "0.24355", "runningtime": "0.00313"}, {"normalization": 2, "date": "shapes", "extrator": "PHOG", "classifier": "Support Vector Machine", "treinamento": "0.60", "teste": "0.58", "precision": "0.70079", "recall": "0.62083", "f1_score": "0.58446", "runningtime": "0.01284"}, {"normalization": 2, "date": "shapes", "extrator": "PHOG", "classifier": "RandomForest", "treinamento": "0.52", "teste": "0.47", "precision": "0.49728", "recall": "0.47778", "f1_score": "0.46241", "runningtime": "0.00689"}, {"normalization": 2, "date": "shapes", "extrator": "PHOG", "classifier": "Neural Net", "treinamento": "0.68", "teste": "0.58", "precision": "0.60185", "recall": "0.59167", "f1_score": "0.58448", "runningtime": "0.00632"}, {"normalization": 2, "date": "shapes", "extrator": "PHOG", "classifier": "Gaussian Naive Bayes", "treinamento": "0.41", "teste": "0.38", "precision": "0.76730", "recall": "0.44167", "f1_score": "0.33977", "runningtime": "0.00434"}, {"normalization": 2, "date": "shapes", "extrator": "PHOG", "classifier": "Logistic Regression", "treinamento": "0.71", "teste": "0.58", "precision": "0.60185", "recall": "0.59167", "f1_score": "0.58448", "runningtime": "0.00298"}, {"normalization": 2, "date": "shapes", "extrator": "PHOG", "classifier": "Decision Tree", "treinamento": "0.46", "teste": "0.50", "precision": "0.51889", "recall": "0.51806", "f1_score": "0.49980", "runningtime": "0.00319"}, {"normalization": 2, "date": "shapes", "extrator": "PHOG", "classifier": "K-Nearest Neighbors", "treinamento": "0.63", "teste": "0.70", "precision": "0.75291", "recall": "0.72917", "f1_score": "0.69841", "runningtime": "0.02389"}, {"normalization": 2, "date": "shapes", "extrator": "PHOG", "classifier": "Linear Discriminant Analysis", "treinamento": "0.29", "teste": "0.25", "precision": "0.22024", "recall": "0.25278", "f1_score": "0.22637", "runningtime": "0.00315"}, {"normalization": 2, "date": "shapes", "extrator": "PHOG", "classifier": "Support Vector Machine", "treinamento": "0.62", "teste": "0.60", "precision": "0.69865", "recall": "0.64167", "f1_score": "0.59249", "runningtime": "0.00559"}, {"normalization": 2, "date": "shapes", "extrator": "PHOG", "classifier": "RandomForest", "treinamento": "0.61", "teste": "0.58", "precision": "0.62522", "recall": "0.61389", "f1_score": "0.58110", "runningtime": "0.00981"}, {"normalization": 2, "date": "shapes", "extrator": "PHOG", "classifier": "Neural Net", "treinamento": "0.69", "teste": "0.63", "precision": "0.65668", "recall": "0.65000", "f1_score": "0.63660", "runningtime": "0.02114"}, {"normalization": 2, "date": "shapes", "extrator": "PHOG", "classifier": "Gaussian Naive Bayes", "treinamento": "0.46", "teste": "0.45", "precision": "0.66408", "recall": "0.49444", "f1_score": "0.43980", "runningtime": "0.00406"}, {"normalization": 2, "date": "shapes", "extrator": "PHOG", "classifier": "Logistic Regression", "treinamento": "0.72", "teste": "0.58", "precision": "0.62588", "recall": "0.59861", "f1_score": "0.58630", "runningtime": "0.00300"}, {"normalization": 2, "date": "shapes", "extrator": "PHOG", "classifier": "Decision Tree", "treinamento": "0.57", "teste": "0.60", "precision": "0.64286", "recall": "0.60972", "f1_score": "0.60215", "runningtime": "0.00304"}, {"normalization": 2, "date": "shapes", "extrator": "PHOG", "classifier": "K-Nearest Neighbors", "treinamento": "0.64", "teste": "0.72", "precision": "0.76522", "recall": "0.74583", "f1_score": "0.71419", "runningtime": "0.01839"}, {"normalization": 2, "date": "shapes", "extrator": "PHOG", "classifier": "Linear Discriminant Analysis", "treinamento": "0.29", "teste": "0.25", "precision": "0.27157", "recall": "0.26250", "f1_score": "0.23662", "runningtime": "0.00659"}, {"normalization": 2, "date": "shapes", "extrator": "PHOG", "classifier": "Support Vector Machine", "treinamento": "0.59", "teste": "0.62", "precision": "0.70617", "recall": "0.65694", "f1_score": "0.60915", "runningtime": "0.01215"}, {"normalization": 2, "date": "shapes", "extrator": "PHOG", "classifier": "RandomForest", "treinamento": "0.58", "teste": "0.57", "precision": "0.59598", "recall": "0.59444", "f1_score": "0.57324", "runningtime": "0.01337"}, {"normalization": 2, "date": "shapes", "extrator": "PHOG", "classifier": "Neural Net", "treinamento": "0.71", "teste": "0.60", "precision": "0.62469", "recall": "0.60833", "f1_score": "0.59979", "runningtime": "0.00509"}, {"normalization": 2, "date": "shapes", "extrator": "PHOG", "classifier": "Gaussian Naive Bayes", "treinamento": "0.54", "teste": "0.57", "precision": "0.69602", "recall": "0.60417", "f1_score": "0.55198", "runningtime": "0.00487"}, {"normalization": 2, "date": "shapes", "extrator": "PHOG", "classifier": "Logistic Regression", "treinamento": "0.71", "teste": "0.58", "precision": "0.62588", "recall": "0.59861", "f1_score": "0.58630", "runningtime": "0.00380"}, {"normalization": 2, "date": "shapes", "extrator": "PHOG", "classifier": "Decision Tree", "treinamento": "0.59", "teste": "0.58", "precision": "0.63378", "recall": "0.59583", "f1_score": "0.58607", "runningtime": "0.00389"}, {"normalization": 2, "date": "shapes", "extrator": "PHOG", "classifier": "K-Nearest Neighbors", "treinamento": "0.64", "teste": "0.68", "precision": "0.74667", "recall": "0.71806", "f1_score": "0.67702", "runningtime": "0.02067"}, {"normalization": 2, "date": "shapes", "extrator": "PHOG", "classifier": "Linear Discriminant Analysis", "treinamento": "0.36", "teste": "0.33", "precision": "0.37455", "recall": "0.35139", "f1_score": "0.32660", "runningtime": "0.00408"}, {"normalization": 2, "date": "shapes", "extrator": "PHOG", "classifier": "Support Vector Machine", "treinamento": "0.63", "teste": "0.65", "precision": "0.73463", "recall": "0.69028", "f1_score": "0.64076", "runningtime": "0.00762"}, {"normalization": 2, "date": "shapes", "extrator": "PHOG", "classifier": "RandomForest", "treinamento": "0.65", "teste": "0.73", "precision": "0.77730", "recall": "0.76806", "f1_score": "0.72952", "runningtime": "0.00784"}, {"normalization": 2, "date": "shapes", "extrator": "PHOG", "classifier": "Neural Net", "treinamento": "0.69", "teste": "0.65", "precision": "0.68305", "recall": "0.66944", "f1_score": "0.64899", "runningtime": "0.00371"}]